dot/__init__.py
dot/config.py
dot/core.py
dot/dot.py
dotfile-0.9.0.dist-info/LICENSE
dotfile-0.9.0.dist-info/METADATA
dotfile-0.9.0.dist-info/WHEEL
dotfile-0.9.0.dist-info/entry_points.txt
dotfile-0.9.0.dist-info/top_level.txt
dotfile-0.9.0.dist-info/RECORD
