Metadata-Version: 2.1
Name: dotfile
Version: 0.9.0
Summary: dot is a git wrapper for managing dotfiles
Home-page: https://github.com/kylepollina/dot
Author: Kyle Pollina
Author-email: kylepollina@pm.me
License: MIT
Platform: UNKNOWN
Classifier: License :: OSI Approved :: MIT License
Classifier: Programming Language :: Python :: 3
Classifier: Programming Language :: Python :: 3.7
